RobotLockable/Remote.py
RobotLockable/RobotLockable.py
RobotLockable/__init__.py
robot_lockable-0.3.3.dist-info/METADATA
robot_lockable-0.3.3.dist-info/WHEEL
robot_lockable-0.3.3.dist-info/entry_points.txt
robot_lockable-0.3.3.dist-info/top_level.txt
robot_lockable-0.3.3.dist-info/RECORD
