Metadata-Version: 2.1
Name: robot-lockable
Version: 0.3.3
Summary: Robot Framework plugin for lockable resources
Home-page: https://github.com/jupe/robot-lockable
Author: Jussi Vatjus-Anttila
Author-email: jussiva@gmail.com
License: MIT
Project-URL: Bug Reports, https://github.com/jupe/robot-lockable
Project-URL: Source, https://github.com/jupe/robot-lockable/
Keywords: robot-framework lockable framework resource
Platform: UNKNOWN
Classifier: Development Status :: 3 - Alpha
Classifier: Topic :: Software Development :: Testing
Classifier: Operating System :: OS Independent
Classifier: License :: OSI Approved :: Apache Software License
Classifier: Operating System :: POSIX
Classifier: Operating System :: Microsoft :: Windows
Classifier: Operating System :: MacOS :: MacOS X
Classifier: Programming Language :: Python
Classifier: Programming Language :: Python :: 3
Classifier: Programming Language :: Python :: 3.6
Classifier: Programming Language :: Python :: 3.7
Classifier: Topic :: Software Development :: Testing
Classifier: Framework :: Robot Framework
Classifier: Framework :: Robot Framework :: Library
Requires-Python: >=3.6
Requires-Dist: robotframework
Requires-Dist: lockable (==0.5.0)
Requires-Dist: click
Requires-Dist: retry
Requires-Dist: robotremoteserver
Requires-Dist: asyncio
Provides-Extra: dev
Requires-Dist: coverage ; extra == 'dev'
Requires-Dist: coveralls ; extra == 'dev'
Requires-Dist: mock ; extra == 'dev'
Requires-Dist: pylint ; extra == 'dev'
Requires-Dist: nose ; extra == 'dev'
Requires-Dist: pyinstaller ; extra == 'dev'
